sgeparse/__init__.py
sgeparse/parser.py
sgeparse/query.py
sgeparse-0.0.2.dist-info/DESCRIPTION.rst
sgeparse-0.0.2.dist-info/METADATA
sgeparse-0.0.2.dist-info/metadata.json
sgeparse-0.0.2.dist-info/RECORD
sgeparse-0.0.2.dist-info/top_level.txt
sgeparse-0.0.2.dist-info/WHEEL
